nonebot_plugin_simulator_xiuxian/__init__.py
nonebot_plugin_simulator_xiuxian-1.5.32.dist-info/LICENSE
nonebot_plugin_simulator_xiuxian-1.5.32.dist-info/METADATA
nonebot_plugin_simulator_xiuxian-1.5.32.dist-info/WHEEL
nonebot_plugin_simulator_xiuxian-1.5.32.dist-info/top_level.txt
nonebot_plugin_simulator_xiuxian-1.5.32.dist-info/RECORD
