Metadata-Version: 2.1
Name: nonebot_plugin_simulator_xiuxian
Version: 1.5.32
Summary: 修仙
Home-page: https://github.com/luoyefufeng/nonebot_plugin_simulator_xiuxian
Author: 甘城菜月
Author-email: 2859385794@qq.com
License: MIT license
Platform: all
License-File: LICENSE
Requires-Dist: nonebot2
Requires-Dist: nonebot-adapter-onebot
Requires-Dist: wget
Requires-Dist: nonebot-plugin-apscheduler
Requires-Dist: Pillow ==9.5.0
Requires-Dist: pydantic
Requires-Dist: wcwidth
Requires-Dist: ujson
Requires-Dist: xiuxianxiuxian-base
Requires-Dist: xiuxian-bank
Requires-Dist: xiuxian-base
Requires-Dist: xiuxian-boss
Requires-Dist: xiuxian-buff
Requires-Dist: xiuxian-info
Requires-Dist: xiuxian-mixelixir
Requires-Dist: xiuxian-rift
Requires-Dist: xiuxian-sect
Requires-Dist: xiuxian-work
